README.md
herdingspikes/.commit_version
herdingspikes/__init__.py
herdingspikes/hs2.py
herdingspikes/parameter_optimisation.py
herdingspikes/probe.py
herdingspikes/version.py
herdingspikes/clustering/__init__.py
herdingspikes/clustering/mean_shift_.py
herdingspikes/detection_localisation/FilterSpikes.cpp
herdingspikes/detection_localisation/FilterSpikes.h
herdingspikes/detection_localisation/LocalizeSpikes.cpp
herdingspikes/detection_localisation/LocalizeSpikes.h
herdingspikes/detection_localisation/Parameters.h
herdingspikes/detection_localisation/ProcessSpikes.cpp
herdingspikes/detection_localisation/ProcessSpikes.h
herdingspikes/detection_localisation/SpikeHandler.cpp
herdingspikes/detection_localisation/SpikeHandler.h
herdingspikes/detection_localisation/SpkDonline.cpp
herdingspikes/detection_localisation/SpkDonline.h
herdingspikes/detection_localisation/__init__.py
herdingspikes/detection_localisation/detect.cpp
herdingspikes/detection_localisation/detect.cpython-310-darwin.so
herdingspikes/detection_localisation/detect.pyx
herdingspikes/detection_localisation/detect_python3.cpp
herdingspikes/probe_functions/__init__.py
herdingspikes/probe_functions/neighborMatrixUtils.py
herdingspikes/probe_functions/readUtils.py
herdingspikes/probe_info/neighbormatrix_biocam
herdingspikes/probe_info/positions_biocam
herdingspikes-0.3.100.dist-info/LICENSE
herdingspikes-0.3.100.dist-info/METADATA
herdingspikes-0.3.100.dist-info/WHEEL
herdingspikes-0.3.100.dist-info/top_level.txt
herdingspikes-0.3.100.dist-info/RECORD
