Metadata-Version: 2.1
Name: herdingspikes
Version: 0.3.100
Summary: Efficient spike detection and sorting for dense MEA
Home-page: https://github.com/mhhennig/HS2
Author: Matthias Hennig Lab, University of Edinburgh
Author-email: m.hennig@ed.ac.uk
License: UNKNOWN
Project-URL: Source, https://github.com/mhhennig/HS2/
Keywords: spikes sorting electrophysiology detection
Platform: UNKNOWN
Classifier: Development Status :: 4 - Beta
Classifier: License :: OSI Approved :: GNU General Public License v3 (GPLv3)
Classifier: Programming Language :: Python :: 3
Classifier: Programming Language :: Python :: 3.6
Classifier: Programming Language :: Python :: 3.7
Classifier: Programming Language :: Python :: 3.8
Classifier: Programming Language :: Python :: 3.9
Requires-Python: >=3.6
License-File: LICENSE
Requires-Dist: h5py
Requires-Dist: matplotlib (>=2.0)
Requires-Dist: pandas
Requires-Dist: scikit-learn (>=0.19.1)
Requires-Dist: joblib
Requires-Dist: six
